sample_adds/__init__.py
sample_adds/add.py
srcs-0.0.2.dist-info/LICENSE
srcs-0.0.2.dist-info/METADATA
srcs-0.0.2.dist-info/WHEEL
srcs-0.0.2.dist-info/top_level.txt
srcs-0.0.2.dist-info/RECORD
