Metadata-Version: 2.1
Name: srcs
Version: 0.0.2
Summary: Addition of two numbers
Author: Sandeep Panchal
Author-email: sandeep.panchal545@gmail.com
License: UNKNOWN
Keywords: "Addition"
Platform: UNKNOWN
Classifier: Programming Language :: Python :: 3
Classifier: License :: OSI Approved :: MIT License
Classifier: Operating System :: OS Independent
Classifier: Intended Audience :: Developers
Requires-Python: >=3
License-File: LICENSE
